LearningRobot/__init__.py
LearningRobot-0.0.0.dev0.dist-info/DESCRIPTION.rst
LearningRobot-0.0.0.dev0.dist-info/METADATA
LearningRobot-0.0.0.dev0.dist-info/metadata.json
LearningRobot-0.0.0.dev0.dist-info/RECORD
LearningRobot-0.0.0.dev0.dist-info/top_level.txt
LearningRobot-0.0.0.dev0.dist-info/WHEEL
