Metadata-Version: 2.0
Name: LearningRobot
Version: 0.0.0.dev0
Summary: Robotics-related Probabilistic Reasoning & Machine Learning
Home-page: https://github.com/MBALearnsToCode/LearningRobot
Author: Vinh Luong (a.k.a. MBALearnsToCode)
Author-email: MBALearnsToCode@UChicago.edu
License: MIT License
Keywords: robot prob reason learning
Platform: UNKNOWN
Requires-Dist: ProbabPyReason
